musecbox/__init__.py
musecbox/__main__.py
musecbox/audio_recorder.py
musecbox/liquidsfz.py
musecbox/score_fixer.py
musecbox/sfz_previewer.py
musecbox/sfzdb.py
musecbox/dialogs/__init__
musecbox/dialogs/add_group_dialog.py
musecbox/dialogs/add_group_dialog.ui
musecbox/dialogs/connection_dialog.py
musecbox/dialogs/connection_dialog.ui
musecbox/dialogs/copy_sfz_paths_dialog.py
musecbox/dialogs/copy_sfzs_dialog.py
musecbox/dialogs/copy_sfzs_dialog.ui
musecbox/dialogs/generic_plugin_dialog.py
musecbox/dialogs/instrument_selection_dialog.py
musecbox/dialogs/instrument_selection_dialog.ui
musecbox/dialogs/missing_sfzs_dialog.py
musecbox/dialogs/project_info_dialog.py
musecbox/dialogs/project_info_dialog.ui
musecbox/dialogs/project_load_dialog.py
musecbox/dialogs/project_load_dialog.ui
musecbox/dialogs/project_save_dialog.py
musecbox/dialogs/record_dialog.py
musecbox/dialogs/record_dialog.ui
musecbox/dialogs/score_apply_dialog.py
musecbox/dialogs/score_apply_dialog.ui
musecbox/dialogs/score_import_channel_widget.ui
musecbox/dialogs/score_import_dialog.py
musecbox/dialogs/score_import_dialog.ui
musecbox/dialogs/score_import_part_widget.ui
musecbox/dialogs/score_info_dialog.py
musecbox/dialogs/score_info_dialog.ui
musecbox/dialogs/score_load_dialog.py
musecbox/dialogs/sfz_file_dialog.py
musecbox/dialogs/sfz_file_dialog.ui
musecbox/dialogs/sfzdb_dialog.py
musecbox/dialogs/sfzdb_dialog.ui
musecbox/dialogs/track_creation_dialog.py
musecbox/dialogs/track_creation_dialog.ui
musecbox/gui/__init__.py
musecbox/gui/balance_control_widget.py
musecbox/gui/horizontal_port_widget.ui
musecbox/gui/horizontal_track_plugin_widget.ui
musecbox/gui/horizontal_track_widget.ui
musecbox/gui/main_window.py
musecbox/gui/main_window.ui
musecbox/gui/plugin_widgets.py
musecbox/gui/port_widget.py
musecbox/gui/shared_plugin_widget.ui
musecbox/gui/track_widget.py
musecbox/gui/vertical_port_widget.ui
musecbox/gui/vertical_track_plugin_widget.ui
musecbox/gui/vertical_track_widget.ui
musecbox-0.6.1.dist-info/entry_points.txt
musecbox-0.6.1.dist-info/LICENSE
musecbox-0.6.1.dist-info/WHEEL
musecbox-0.6.1.dist-info/METADATA
musecbox-0.6.1.dist-info/RECORD
