Metadata-Version: 2.1
Name: musecbox
Version: 0.6.1
Summary: "MusecBox" is A GUI application designed to be an SFZ -based synth replacement
Author-email: Leon Dionne <ldionne@dridesign.sh.cn>
Classifier: License :: OSI Approved :: GNU General Public License v3 or later (GPLv3+)
Requires-Dist: PyQt5
Requires-Dist: appdirs
Requires-Dist: simple_carla >= 2.6.0
Requires-Dist: JACK-Client >= 0.5.0
Requires-Dist: mscore3 >= 1.11.1
Requires-Dist: sfzen >= 1.7.0
Requires-Dist: recent_items_list >= 1.1.0
Requires-Dist: soso_qt_extras >= 1.4.0
Requires-Dist: log_soso
Project-URL: Home, https://github.com/Zen-Master-SoSo/musecbox
